statfit/__init__.py
statfit/gaussian_fit.py
tests/__init__.py
tests/test_gaussian_fit.py
statfit-1.0.dist-info/LICENSE
statfit-1.0.dist-info/METADATA
statfit-1.0.dist-info/WHEEL
statfit-1.0.dist-info/top_level.txt
statfit-1.0.dist-info/RECORD
